[
  {
    "tag_name": "entity",
    "ids_to_tags": {
      "1": "B-nome_documeno",
      "2": "I-nome_documeno",
      "3": "L-nome_documeno",
      "4": "U-nome_documeno",
      "5": "B-nome_documento",
      "6": "I-nome_documento",
      "7": "L-nome_documento",
      "8": "U-nome_documento",
      "9": "B-number",
      "10": "I-number",
      "11": "L-number",
      "12": "U-number",
      "13": "B-person_name",
      "14": "I-person_name",
      "15": "L-person_name",
      "16": "U-person_name",
      "0": "O"
    },
    "tags_to_ids": {
      "B-nome_documeno": 1,
      "I-nome_documeno": 2,
      "L-nome_documeno": 3,
      "U-nome_documeno": 4,
      "B-nome_documento": 5,
      "I-nome_documento": 6,
      "L-nome_documento": 7,
      "U-nome_documento": 8,
      "B-number": 9,
      "I-number": 10,
      "L-number": 11,
      "U-number": 12,
      "B-person_name": 13,
      "I-person_name": 14,
      "L-person_name": 15,
      "U-person_name": 16,
      "O": 0
    },
    "num_tags": 17
  }
]